{
  "id": "1274678",
  "name": "幸福里图标",
  "font_family": "F100",
  "css_prefix_text": "icon",
  "description": "",
  "glyphs": [
    {
      "icon_id": "11287894",
      "name": "发送@2x",
      "font_class": "fasongx",
      "unicode": "e6c3",
      "unicode_decimal": 59075
    },
    {
      "icon_id": "11103247",
      "name": "icon_delete_light_normal@3x",
      "font_class": "icon_delete_light_normalx",
      "unicode": "e6be",
      "unicode_decimal": 59070
    },
    {
      "icon_id": "11103248",
      "name": "icon_jubao_light_normal@3x",
      "font_class": "icon_jubao_light_normalx",
      "unicode": "e6bf",
      "unicode_decimal": 59071
    },
    {
      "icon_id": "11103249",
      "name": "icon_top_light_normal@3x",
      "font_class": "icon_top_light_normalx",
      "unicode": "e6c0",
      "unicode_decimal": 59072
    },
    {
      "icon_id": "11103250",
      "name": "icon_jiajing_light_normal@3x",
      "font_class": "icon_jiajing_light_normalx",
      "unicode": "e6c1",
      "unicode_decimal": 59073
    },
    {
      "icon_id": "11103251",
      "name": "icon_zijian_light_normal@3x",
      "font_class": "icon_zijian_light_normalx",
      "unicode": "e6c2",
      "unicode_decimal": 59074
    },
    {
      "icon_id": "10275988",
      "name": "delete copy@3x",
      "font_class": "deletecopyx",
      "unicode": "e6bb",
      "unicode_decimal": 59067
    },
    {
      "icon_id": "10275961",
      "name": "icon_more_noraml@3x",
      "font_class": "icon_more_noramlx1",
      "unicode": "e6bc",
      "unicode_decimal": 59068
    },
    {
      "icon_id": "10275971",
      "name": "icon_location_s_normal@3x",
      "font_class": "icon_location_s_normalx",
      "unicode": "e6bd",
      "unicode_decimal": 59069
    },
    {
      "icon_id": "10275941",
      "name": "icon_close_black_normal@3x",
      "font_class": "icon_close_black_normalx",
      "unicode": "e678",
      "unicode_decimal": 59000
    },
    {
      "icon_id": "10275942",
      "name": "icon_anwser_red_normal@3x",
      "font_class": "icon_anwser_red_normalx",
      "unicode": "e6b3",
      "unicode_decimal": 59059
    },
    {
      "icon_id": "10275943",
      "name": "icon_search_black_normal@3x",
      "font_class": "icon_search_black_normalx",
      "unicode": "e6b4",
      "unicode_decimal": 59060
    },
    {
      "icon_id": "10275944",
      "name": "ic_navigation_pic_normal@3x",
      "font_class": "ic_navigation_pic_normalx",
      "unicode": "e6b5",
      "unicode_decimal": 59061
    },
    {
      "icon_id": "10275945",
      "name": "ic_navigation_keyboard_selected@3x",
      "font_class": "ic_navigation_keyboard_selectedx",
      "unicode": "e6b6",
      "unicode_decimal": 59062
    },
    {
      "icon_id": "10275946",
      "name": "icon_refresh_black_normal@3x",
      "font_class": "icon_refresh_black_normalx",
      "unicode": "e6b7",
      "unicode_decimal": 59063
    },
    {
      "icon_id": "10275947",
      "name": "ic_navigation_huati_normal@3x",
      "font_class": "ic_navigation_huati_normalx",
      "unicode": "e6b8",
      "unicode_decimal": 59064
    },
    {
      "icon_id": "10275948",
      "name": "ic_navigation_keyboard_normal@3x",
      "font_class": "ic_navigation_keyboard_normalx",
      "unicode": "e6b9",
      "unicode_decimal": 59065
    },
    {
      "icon_id": "10275949",
      "name": "ic_navigation_smile_normal@3x",
      "font_class": "ic_navigation_smile_normalx",
      "unicode": "e6ba",
      "unicode_decimal": 59066
    },
    {
      "icon_id": "10081032",
      "name": "选中@2x",
      "font_class": "xuanzhongx1",
      "unicode": "e6b2",
      "unicode_decimal": 59058
    },
    {
      "icon_id": "10074290",
      "name": "刷新@2x",
      "font_class": "shuaxinx",
      "unicode": "e6ac",
      "unicode_decimal": 59052
    },
    {
      "icon_id": "10074068",
      "name": "一般@2x",
      "font_class": "yibanx",
      "unicode": "e66b",
      "unicode_decimal": 58987
    },
    {
      "icon_id": "10074069",
      "name": "不专业@2x",
      "font_class": "buzhuanyex",
      "unicode": "e6ae",
      "unicode_decimal": 59054
    },
    {
      "icon_id": "10074070",
      "name": "add to@2x",
      "font_class": "addtox",
      "unicode": "e652",
      "unicode_decimal": 58962
    },
    {
      "icon_id": "10074071",
      "name": "筛选@2x",
      "font_class": "shaixuanx",
      "unicode": "e68d",
      "unicode_decimal": 59021
    },
    {
      "icon_id": "10074072",
      "name": "编辑@2x",
      "font_class": "bianjix",
      "unicode": "e681",
      "unicode_decimal": 59009
    },
    {
      "icon_id": "10074073",
      "name": "专业@2x",
      "font_class": "zhuanyex",
      "unicode": "e6af",
      "unicode_decimal": 59055
    },
    {
      "icon_id": "10074074",
      "name": "开盘通知@2x",
      "font_class": "kaipantongzhix",
      "unicode": "e68e",
      "unicode_decimal": 59022
    },
    {
      "icon_id": "10074075",
      "name": "定位2@2x",
      "font_class": "dingweix",
      "unicode": "e667",
      "unicode_decimal": 58983
    },
    {
      "icon_id": "10074076",
      "name": "收藏@2x",
      "font_class": "shoucangx",
      "unicode": "e696",
      "unicode_decimal": 59030
    },
    {
      "icon_id": "10074077",
      "name": "画圈@2x",
      "font_class": "huaquanx",
      "unicode": "e67c",
      "unicode_decimal": 59004
    },
    {
      "icon_id": "10074078",
      "name": "搜索_删除@2x",
      "font_class": "sousuo_shanchux",
      "unicode": "e66f",
      "unicode_decimal": 58991
    },
    {
      "icon_id": "10074079",
      "name": "电话1@2x",
      "font_class": "dianhuax1",
      "unicode": "e69a",
      "unicode_decimal": 59034
    },
    {
      "icon_id": "10074080",
      "name": "返回@2x",
      "font_class": "fanhuix",
      "unicode": "e68a",
      "unicode_decimal": 59018
    },
    {
      "icon_id": "10074081",
      "name": "expression@2x",
      "font_class": "expressionx",
      "unicode": "e651",
      "unicode_decimal": 58961
    },
    {
      "icon_id": "10074082",
      "name": "变价通知@2x",
      "font_class": "bianjiatongzhix",
      "unicode": "e67e",
      "unicode_decimal": 59006
    },
    {
      "icon_id": "10074084",
      "name": "关闭@2x",
      "font_class": "guanbix",
      "unicode": "e673",
      "unicode_decimal": 58995
    },
    {
      "icon_id": "10074085",
      "name": "keyboard@2x",
      "font_class": "keyboardx",
      "unicode": "e653",
      "unicode_decimal": 58963
    },
    {
      "icon_id": "10074086",
      "name": "舒适@2x",
      "font_class": "shushix",
      "unicode": "e661",
      "unicode_decimal": 58977
    },
    {
      "icon_id": "10074087",
      "name": "搜索_搜索@2x",
      "font_class": "sousuo_sousuox",
      "unicode": "e690",
      "unicode_decimal": 59024
    },
    {
      "icon_id": "10074088",
      "name": "分享@2x",
      "font_class": "fenxiangx",
      "unicode": "e692",
      "unicode_decimal": 59026
    },
    {
      "icon_id": "10074089",
      "name": "错误提示@2x",
      "font_class": "cuowutishix",
      "unicode": "e668",
      "unicode_decimal": 58984
    },
    {
      "icon_id": "10074090",
      "name": "勾选框@2x",
      "font_class": "gouxuankuangx",
      "unicode": "e689",
      "unicode_decimal": 59017
    },
    {
      "icon_id": "10074091",
      "name": "地图@2x",
      "font_class": "ditux",
      "unicode": "e66a",
      "unicode_decimal": 58986
    },
    {
      "icon_id": "10074092",
      "name": "定位@2x",
      "font_class": "dingweix1",
      "unicode": "e66c",
      "unicode_decimal": 58988
    },
    {
      "icon_id": "10074094",
      "name": "地图_医院@2x",
      "font_class": "ditu_yiyuanx",
      "unicode": "e66d",
      "unicode_decimal": 58989
    },
    {
      "icon_id": "10074095",
      "name": "列表@2x",
      "font_class": "liebiaox",
      "unicode": "e679",
      "unicode_decimal": 59001
    },
    {
      "icon_id": "10074096",
      "name": "左箭头@2x",
      "font_class": "zuojiantoux",
      "unicode": "e68c",
      "unicode_decimal": 59020
    },
    {
      "icon_id": "10074098",
      "name": "顺序@2x",
      "font_class": "shunxux",
      "unicode": "e67a",
      "unicode_decimal": 59002
    },
    {
      "icon_id": "10074101",
      "name": "容积率@2x",
      "font_class": "rongjishuaix",
      "unicode": "e663",
      "unicode_decimal": 58979
    },
    {
      "icon_id": "10074102",
      "name": "信息@2x",
      "font_class": "xinxix",
      "unicode": "e691",
      "unicode_decimal": 59025
    },
    {
      "icon_id": "10074103",
      "name": "地图_美食@2x",
      "font_class": "ditu_meishix",
      "unicode": "e665",
      "unicode_decimal": 58981
    },
    {
      "icon_id": "10074104",
      "name": "学校资源@2x",
      "font_class": "xuexiaoziyuanx",
      "unicode": "e676",
      "unicode_decimal": 58998
    },
    {
      "icon_id": "10074105",
      "name": "loading@2x",
      "font_class": "loadingx",
      "unicode": "e65e",
      "unicode_decimal": 58974
    },
    {
      "icon_id": "10074106",
      "name": "消息1@2x",
      "font_class": "xiaoxix",
      "unicode": "e699",
      "unicode_decimal": 59033
    },
    {
      "icon_id": "10074108",
      "name": "物业费@2x",
      "font_class": "wuyefeix",
      "unicode": "e664",
      "unicode_decimal": 58980
    },
    {
      "icon_id": "10074109",
      "name": "正确@2x",
      "font_class": "zhengquex",
      "unicode": "e666",
      "unicode_decimal": 58982
    },
    {
      "icon_id": "10074111",
      "name": "右箭头@2x",
      "font_class": "youjiantoux",
      "unicode": "e670",
      "unicode_decimal": 58992
    },
    {
      "icon_id": "10074112",
      "name": "添加@2x",
      "font_class": "tianjiax",
      "unicode": "e69b",
      "unicode_decimal": 59035
    },
    {
      "icon_id": "10074113",
      "name": "下箭头@2x",
      "font_class": "xiajiantoux",
      "unicode": "e672",
      "unicode_decimal": 58994
    },
    {
      "icon_id": "10074115",
      "name": "地图_地铁@2x",
      "font_class": "ditu_ditiex",
      "unicode": "e685",
      "unicode_decimal": 59013
    },
    {
      "icon_id": "10074117",
      "name": "地图_银行@2x",
      "font_class": "ditu_yinhangx",
      "unicode": "e67d",
      "unicode_decimal": 59005
    },
    {
      "icon_id": "10074118",
      "name": "规模@2x",
      "font_class": "guimox",
      "unicode": "e662",
      "unicode_decimal": 58978
    },
    {
      "icon_id": "10074119",
      "name": "地图_购物@2x",
      "font_class": "ditu_gouwux",
      "unicode": "e66e",
      "unicode_decimal": 58990
    },
    {
      "icon_id": "10074120",
      "name": "错误@2x",
      "font_class": "cuowux",
      "unicode": "e658",
      "unicode_decimal": 58968
    },
    {
      "icon_id": "10074121",
      "name": "地图_休闲@2x",
      "font_class": "ditu_xiuxianx",
      "unicode": "e6b0",
      "unicode_decimal": 59056
    },
    {
      "icon_id": "10074123",
      "name": "地图_教育@2x",
      "font_class": "ditu_jiaoyux",
      "unicode": "e671",
      "unicode_decimal": 58993
    },
    {
      "icon_id": "10074124",
      "name": "选框@2x",
      "font_class": "xuankuangx",
      "unicode": "e669",
      "unicode_decimal": 58985
    },
    {
      "icon_id": "10074125",
      "name": "上箭头@2x",
      "font_class": "shangjiantoux",
      "unicode": "e65f",
      "unicode_decimal": 58975
    },
    {
      "icon_id": "10074126",
      "name": "地图_游泳@2x",
      "font_class": "ditu_youyongx",
      "unicode": "e65d",
      "unicode_decimal": 58973
    },
    {
      "icon_id": "10074127",
      "name": "点赞@2x",
      "font_class": "dianzanx",
      "unicode": "e69c",
      "unicode_decimal": 59036
    },
    {
      "icon_id": "10074128",
      "name": "举报@2x",
      "font_class": "jubaox",
      "unicode": "e682",
      "unicode_decimal": 59010
    },
    {
      "icon_id": "10074129",
      "name": "地图_公交@2x",
      "font_class": "ditu_gongjiaox",
      "unicode": "e674",
      "unicode_decimal": 58996
    },
    {
      "icon_id": "10074130",
      "name": "简介@2x",
      "font_class": "jianjiex",
      "unicode": "e6ad",
      "unicode_decimal": 59053
    },
    {
      "icon_id": "10073848",
      "name": "选中@2x",
      "font_class": "xuanzhongx",
      "unicode": "e6b1",
      "unicode_decimal": 59057
    },
    {
      "icon_id": "9736298",
      "name": "ic_map_subway_round@2x",
      "font_class": "ic_map_subway_roundx",
      "unicode": "e6a2",
      "unicode_decimal": 59042
    },
    {
      "icon_id": "9736299",
      "name": "ic_map_fitness_round@2x",
      "font_class": "ic_map_fitness_roundx",
      "unicode": "e6a3",
      "unicode_decimal": 59043
    },
    {
      "icon_id": "9736300",
      "name": "ic_map_shopping_round@2x",
      "font_class": "ic_map_shopping_roundx",
      "unicode": "e6a4",
      "unicode_decimal": 59044
    },
    {
      "icon_id": "9736301",
      "name": "ic_map_leisure_round@2x",
      "font_class": "ic_map_leisure_roundx",
      "unicode": "e6a5",
      "unicode_decimal": 59045
    },
    {
      "icon_id": "9737690",
      "name": "电话_默认@2x",
      "font_class": "dianhua_morenx",
      "unicode": "e6a6",
      "unicode_decimal": 59046
    },
    {
      "icon_id": "9737691",
      "name": "短信_点击@2x",
      "font_class": "duanxin_dianjix",
      "unicode": "e6a7",
      "unicode_decimal": 59047
    },
    {
      "icon_id": "9737692",
      "name": "短信_默认@2x",
      "font_class": "duanxin_morenx",
      "unicode": "e6a8",
      "unicode_decimal": 59048
    },
    {
      "icon_id": "9737693",
      "name": "电话_点击@2x",
      "font_class": "dianhua_dianjix",
      "unicode": "e6a9",
      "unicode_decimal": 59049
    },
    {
      "icon_id": "9737694",
      "name": "电话_无@2x",
      "font_class": "dianhua_wux",
      "unicode": "e6aa",
      "unicode_decimal": 59050
    },
    {
      "icon_id": "9737695",
      "name": "短信_无@2x",
      "font_class": "duanxin_wux",
      "unicode": "e6ab",
      "unicode_decimal": 59051
    },
    {
      "icon_id": "9736133",
      "name": "首页_搜索@2x",
      "font_class": "shouye_sousuox",
      "unicode": "e675",
      "unicode_decimal": 58997
    },
    {
      "icon_id": "9736135",
      "name": "搜索_下拉@2x",
      "font_class": "sousuo_xialax",
      "unicode": "e677",
      "unicode_decimal": 58999
    },
    {
      "icon_id": "9736139",
      "name": "首页_定位@2x",
      "font_class": "shouye_dingweix",
      "unicode": "e67b",
      "unicode_decimal": 59003
    },
    {
      "icon_id": "9736143",
      "name": "搜索_收起@2x",
      "font_class": "sousuo_shouqix",
      "unicode": "e67f",
      "unicode_decimal": 59007
    },
    {
      "icon_id": "9736144",
      "name": "消息_默认@2x",
      "font_class": "xiaoxi_morenx",
      "unicode": "e680",
      "unicode_decimal": 59008
    },
    {
      "icon_id": "9736147",
      "name": "首页_默认@2x",
      "font_class": "shouye_morenx",
      "unicode": "e683",
      "unicode_decimal": 59011
    },
    {
      "icon_id": "9736148",
      "name": "经纪人名片@2x",
      "font_class": "jingjirenmingpianx",
      "unicode": "e684",
      "unicode_decimal": 59012
    },
    {
      "icon_id": "9736150",
      "name": "电话@2x",
      "font_class": "dianhuax",
      "unicode": "e686",
      "unicode_decimal": 59014
    },
    {
      "icon_id": "9736151",
      "name": "置顶@2x",
      "font_class": "zhidingx",
      "unicode": "e687",
      "unicode_decimal": 59015
    },
    {
      "icon_id": "9736152",
      "name": "举报2@2x",
      "font_class": "jubaox1",
      "unicode": "e688",
      "unicode_decimal": 59016
    },
    {
      "icon_id": "9736156",
      "name": "我的_选中@2x",
      "font_class": "wode_xuanzhongx",
      "unicode": "e68b",
      "unicode_decimal": 59019
    },
    {
      "icon_id": "9736160",
      "name": "首页_选中@2x",
      "font_class": "shouye_xuanzhongx",
      "unicode": "e68f",
      "unicode_decimal": 59023
    },
    {
      "icon_id": "9736164",
      "name": "发现@2x",
      "font_class": "faxianx",
      "unicode": "e693",
      "unicode_decimal": 59027
    },
    {
      "icon_id": "9736165",
      "name": "短信@2x",
      "font_class": "duanxinx",
      "unicode": "e694",
      "unicode_decimal": 59028
    },
    {
      "icon_id": "9736166",
      "name": "消息_选中@2x",
      "font_class": "xiaoxi_xuanzhongx",
      "unicode": "e695",
      "unicode_decimal": 59029
    },
    {
      "icon_id": "9736168",
      "name": "我的_默认@2x",
      "font_class": "wode_morenx",
      "unicode": "e697",
      "unicode_decimal": 59031
    },
    {
      "icon_id": "9736169",
      "name": "搜索_清空@2x",
      "font_class": "sousuo_qingkongx",
      "unicode": "e698",
      "unicode_decimal": 59032
    },
    {
      "icon_id": "9736293",
      "name": "ic_map_school_round@2x",
      "font_class": "ic_map_school_roundx",
      "unicode": "e69d",
      "unicode_decimal": 59037
    },
    {
      "icon_id": "9736294",
      "name": "ic_map_hospital_round@2x",
      "font_class": "ic_map_hospital_roundx",
      "unicode": "e69e",
      "unicode_decimal": 59038
    },
    {
      "icon_id": "9736295",
      "name": "ic_map_bus_round@2x",
      "font_class": "ic_map_bus_roundx",
      "unicode": "e69f",
      "unicode_decimal": 59039
    },
    {
      "icon_id": "9736296",
      "name": "ic_map_food_round@2x",
      "font_class": "ic_map_food_roundx",
      "unicode": "e6a0",
      "unicode_decimal": 59040
    },
    {
      "icon_id": "9736297",
      "name": "ic_map_bank_round@2x",
      "font_class": "ic_map_bank_roundx",
      "unicode": "e6a1",
      "unicode_decimal": 59041
    }
  ]
}
